vipps/__init__.py
vipps/vipps_api.py
vipps-0.1.dist-info/LICENSE
vipps-0.1.dist-info/METADATA
vipps-0.1.dist-info/WHEEL
vipps-0.1.dist-info/top_level.txt
vipps-0.1.dist-info/RECORD
