Metadata-Version: 2.1
Name: vipps
Version: 0.1
Summary: Python bindings for the Vipps API
Home-page: https://github.com/almazkun/vipps-python
Author: Almaz Kunpeissov
Author-email: hi@akun.dev
License: MIT License
Project-URL: Documentation, https://github.com/almazkun/vipps-python
Project-URL: Source, https://github.com/almazkun/vipps-python
Project-URL: Tracker, https://github.com/almazkun/vipps-python/issues
Keywords: vipps api payments
Platform: UNKNOWN
Classifier: Development Status :: 2 - Pre-Alpha
Classifier: Intended Audience :: Developers
Classifier: Operating System :: OS Independent
Classifier: Programming Language :: Python :: 3 :: Only
Classifier: Programming Language :: Python :: 3.7
Classifier: Programming Language :: Python :: Implementation :: PyPy
Classifier: Topic :: Software Development :: Libraries :: Python Modules
Requires-Python: >=3.7
Requires-Dist: requests (>=2)
